Metadata-Version: 2.1
Name: gil-load
Version: 0.4.2
Summary: Utility for measuring the fraction of time the GIL is held in a program
Home-page: https://github.com/chrisjbillington/gil_load
Author: Chris Billington
Author-email: chrisjbillington@gmail.com
License: BSD
Platform: UNKNOWN
License-File: LICENSE
